{
    "summary_line": [
        {
        "line": "A",
        "plan": 27482,
        "actual": 18100,
        "pct": 65.9
        },
        {
        "line": "B",
        "plan": 54142,
        "actual": 36322,
        "pct": 67.1
        },
        {
        "line": "C",
        "plan": 48433,
        "actual": 35062,
        "pct": 72.4
        },
        {
        "line": "D",
        "plan": 76810,
        "actual": 59905,
        "pct": 78
        },
        {
        "line": "E",
        "plan": 10714,
        "actual": 7658,
        "pct": 71.5
        },
        {
        "line": "F",
        "plan": 17586,
        "actual": 13880,
        "pct": 78.9
        },
        {
        "line": "G",
        "plan": 23949,
        "actual": 20196,
        "pct": 84.3
        },
        {
        "line": "H",
        "plan": 36892,
        "actual": 30315,
        "pct": 82.2
        },
        {
        "line": "300T",
        "plan": 37852,
        "actual": 29099,
        "pct": 76.9
        },
        {
        "line": "SP",
        "plan": 173595,
        "actual": 129616,
        "pct": 74.7
        },
        {
        "line": "S/A ADM", 
        "plan": 23456,
        "actual": 18000,
        "pct": 76.5
        },
        {
        "line": "S/A HMMI", 
        "plan": 15000,
        "actual": 12000,
        "pct": 80
        },
        {
        "line": "WSS ADM", 
        "plan": 11234,
        "actual": 10000,
        "pct": 89.1
        },
        {
        "line": "WSS MMKI", 
        "plan": 23000,
        "actual": 20500,
        "pct": 89.1
        }
    ],
    "detail_daily": [
        {
        "Stamping": [
                {
                    "line": "A",
                    "daily": [
                    { "date": "2025-09-26", "plan": 3200, "actual": 2500, "pct": "78.1" },
                    { "date": "2025-09-27", "plan": 4300, "actual": 3400, "pct": "79.0" },
                    { "date": "2025-09-28", "plan": 5100, "actual": 4000, "pct": "78.4" },
                    { "date": "2025-09-29", "plan": 9000, "actual": 8700, "pct": "96.6" },
                    { "date": "2025-09-30", "plan": 8200, "actual": 7000, "pct": "85.4" },
                    { "date": "2025-10-01", "plan": 7200, "actual": 6100, "pct": "84.7" },
                    { "date": "2025-10-02", "plan": 6300, "actual": 5400, "pct": "85.7" }
                    
                    ]
                },
                {
                    "line": "B",
                    "daily": [
                    { "date": "2025-09-26", "plan": 7700, "actual": 6000, "pct": "77.9" },
                    { "date": "2025-09-27", "plan": 7900, "actual": 6200, "pct": "78.5" },
                    { "date": "2025-09-28", "plan": 8000, "actual": 6400, "pct": "80.0" },
                    { "date": "2025-09-29", "plan": 8100, "actual": 6500, "pct": "80.2" },
                    { "date": "2025-09-30", "plan": 7800, "actual": 6100, "pct": "78.2" },
                    { "date": "2025-10-01", "plan": 7700, "actual": 6000, "pct": "77.9" },
                    { "date": "2025-10-02", "plan": 7600, "actual": 5900, "pct": "77.6" }
                    ]
                },
                {
                    "line": "C",
                    "daily": [
                    { "date": "2025-09-26", "plan": 6900, "actual": 5000, "pct": "72.5" },
                    { "date": "2025-09-27", "plan": 7100, "actual": 5300, "pct": "74.6" },
                    { "date": "2025-09-28", "plan": 7200, "actual": 5400, "pct": "75.0" },
                    { "date": "2025-09-29", "plan": 7000, "actual": 5200, "pct": "74.3" },
                    { "date": "2025-09-30", "plan": 7100, "actual": 5100, "pct": "71.8" },
                    { "date": "2025-10-01", "plan": 6950, "actual": 5050, "pct": "72.7" },
                    { "date": "2025-10-02", "plan": 7050, "actual": 5150, "pct": "73.0" }
                    ]
                },
                {
                    "line": "D",
                    "daily": [
                    { "date": "2025-09-26", "plan": 11000, "actual": 8700, "pct": "79.1" },
                    { "date": "2025-09-27", "plan": 11100, "actual": 8900, "pct": "80.2" },
                    { "date": "2025-09-28", "plan": 10900, "actual": 8600, "pct": "78.9" },
                    { "date": "2025-09-29", "plan": 11200, "actual": 8800, "pct": "78.6" },
                    { "date": "2025-09-30", "plan": 11300, "actual": 9000, "pct": "79.6" },
                    { "date": "2025-10-01", "plan": 11050, "actual": 8700, "pct": "78.7" },
                    { "date": "2025-10-02", "plan": 10950, "actual": 8600, "pct": "78.5" }
                    ]
                },
                {
                    "line": "E",
                    "daily": [
                    { "date": "2025-09-26", "plan": 1500, "actual": 1100, "pct": "73.3" },
                    { "date": "2025-09-27", "plan": 1550, "actual": 1150, "pct": "74.2" },
                    { "date": "2025-09-28", "plan": 1600, "actual": 1200, "pct": "75.0" },
                    { "date": "2025-09-29", "plan": 1580, "actual": 1180, "pct": "74.7" },
                    { "date": "2025-09-30", "plan": 1570, "actual": 1170, "pct": "74.5" },
                    { "date": "2025-10-01", "plan": 1560, "actual": 1160, "pct": "74.4" },
                    { "date": "2025-10-02", "plan": 1540, "actual": 1140, "pct": "74.0" }
                    ]
                },
                {
                    "line": "F",
                    "daily": [
                    { "date": "2025-09-26", "plan": 2500, "actual": 1900, "pct": "76.0" },
                    { "date": "2025-09-27", "plan": 2550, "actual": 1950, "pct": "76.5" },
                    { "date": "2025-09-28", "plan": 2600, "actual": 2000, "pct": "76.9" },
                    { "date": "2025-09-29", "plan": 2650, "actual": 2050, "pct": "77.4" },
                    { "date": "2025-09-30", "plan": 2700, "actual": 2100, "pct": "77.8" },
                    { "date": "2025-10-01", "plan": 2680, "actual": 2080, "pct": "77.6" },
                    { "date": "2025-10-02", "plan": 2660, "actual": 2060, "pct": "77.4" }
                    ]
                },
                {
                    "line": "G",
                    "daily": [
                    { "date": "2025-09-26", "plan": 3400, "actual": 2900, "pct": "85.3" },
                    { "date": "2025-09-27", "plan": 3450, "actual": 2950, "pct": "85.5" },
                    { "date": "2025-09-28", "plan": 3500, "actual": 3000, "pct": "85.7" },
                    { "date": "2025-09-29", "plan": 3550, "actual": 3050, "pct": "85.9" },
                    { "date": "2025-09-30", "plan": 3520, "actual": 3020, "pct": "85.8" },
                    { "date": "2025-10-01", "plan": 3480, "actual": 2980, "pct": "85.6" },
                    { "date": "2025-10-02", "plan": 3460, "actual": 2960, "pct": "85.5" }
                    ]
                },
                {
                    "line": "H",
                    "daily": [
                        { "date": "2025-09-26", "plan": 5300, "actual": 4400, "pct": "83.0" },
                        { "date": "2025-09-27", "plan": 5400, "actual": 4500, "pct": "83.3" },
                        { "date": "2025-09-28", "plan": 5500, "actual": 4600, "pct": "83.6" },
                        { "date": "2025-09-29", "plan": 5600, "actual": 4700, "pct": "83.9" },
                        { "date": "2025-09-30", "plan": 5550, "actual": 4650, "pct": "83.8" },
                        { "date": "2025-10-01", "plan": 5450, "actual": 4550, "pct": "83.5" },
                        { "date": "2025-10-02", "plan": 5400, "actual": 4500, "pct": "83.3" }
                    ]
                },
                {
                    "line": "300T",
                    "daily": [
                    { "date": "2025-09-26", "plan": 5400, "actual": 4200, "pct": "77.8" },
                    { "date": "2025-09-27", "plan": 6350, "actual": 5000, "pct": "78.7" },
                    { "date": "2025-09-28", "plan": 7200, "actual": 6100, "pct": "84.7" },
                    { "date": "2025-09-29", "plan": 11000, "actual": 9400, "pct": "85.4" },
                    { "date": "2025-09-30", "plan": 10400, "actual": 8900, "pct": "85.6" },
                    { "date": "2025-10-01", "plan": 9300, "actual": 8100, "pct": "87.1" },
                    { "date": "2025-10-02", "plan": 8500, "actual": 7300, "pct": "85.9" }
                    ]
                },
                {
                    "line": "SP",
                    "daily": [
                    { "date": "2025-09-26", "plan": 24800, "actual": 19000, "pct": "76.6" },
                    { "date": "2025-09-27", "plan": 25000, "actual": 18200, "pct": "72.8" },
                    { "date": "2025-09-28", "plan": 24900, "actual": 18800, "pct": "75.5" },
                    { "date": "2025-09-29", "plan": 25200, "actual": 20000, "pct": "79.4" },
                    { "date": "2025-09-30", "plan": 25100, "actual": 19200, "pct": "76.5" },
                    { "date": "2025-10-01", "plan": 25050, "actual": 18700, "pct": "74.6" },
                    { "date": "2025-10-02", "plan": 24950, "actual": 18950, "pct": "76.0" }
                    ]
                }
            ]
        },
        {
            "Welding": [
                {
                    "line": "S/A ADM",
                    "daily": [
                        { "date": "2025-09-26", "plan": 3000, "actual": 2700, "pct": "90.0" },
                        { "date": "2025-09-27", "plan": 3000, "actual": 2800, "pct": "93.3" },
                        { "date": "2025-09-28", "plan": 3000, "actual": 2900, "pct": "96.7" },
                        { "date": "2025-09-29", "plan": 3000, "actual": 2950, "pct": "98.3" },
                        { "date": "2025-09-30", "plan": 3000, "actual": 2950, "pct": "98.3" },
                        { "date": "2025-10-01", "plan": 3000, "actual": 2900, "pct": "96.7" },
                        { "date": "2025-10-02", "plan": 3000, "actual": 2700, "pct": "90.0" }
                    ]
                },
                {
                    "line": "S/A HMMI",
                    "daily": [
                        { "date": "2025-09-26", "plan": 2500, "actual": 2300, "pct": "92.0" },
                        { "date": "2025-09-27", "plan": 2500, "actual": 2400, "pct": "96.0" },
                        { "date": "2025-09-28", "plan": 2500, "actual": 2450, "pct": "98.0" },
                        { "date": "2025-09-29", "plan": 2500, "actual": 2500, "pct": "100.0" },
                        { "date": "2025-09-30", "plan": 2500, "actual": 2450, "pct": "98.0" },
                        { "date": "2025-10-01", "plan": 2500, "actual": 2400, "pct": "96.0" },
                        { "date": "2025-10-02", "plan": 2500, "actual": 2300, "pct": "92.0" }
                    ]
                },
                {
                    "line": "WSS ADM",
                    "daily": [
                        { "date": "2025-09-26", "plan": 2000, "actual": 1800, "pct": "90.0" },
                        { "date": "2025-09-27", "plan": 2000, "actual": 1900, "pct": "95.0" },
                        { "date": "2025-09-28", "plan": 2000, "actual": 1950, "pct": "97.5" },
                        { "date": "2025-09-29", "plan": 2000, "actual": 2000, "pct": "100.0" },
                        { "date": "2025-09-30", "plan": 2000, "actual": 1950, "pct": "97.5" },
                        { "date": "2025-10-01", "plan": 2000, "actual": 1900, "pct": "95.0" },
                        { "date": "2025-10-02", "plan": 2000, "actual": 1800, "pct": "90.0" }
                    ]
                },
                {
                    "line": "WSS MMKI",
                    "daily": [
                        { "date": "2025-09-26", "plan": 1700, "actual": 1600, "pct": "94.1" },
                        { "date": "2025-09-27", "plan": 1700, "actual": 1650, "pct": "97.1" },
                        { "date": "2025-09-28", "plan": 1700, "actual": 1750, "pct": "102.9" },
                        { "date": "2025-09-29", "plan": 1700, "actual": 1800, "pct": "105.9" },
                        { "date": "2025-09-30", "plan": 1700, "actual": 1650, "pct": "97.1" },
                        { "date": "2025-10-01", "plan": 1700, "actual": 1600, "pct": "94.1" },
                        { "date": "2025-10-02", "plan": 1700, "actual": 1500, "pct": "88.2" }
                    ]
                }
            ]
        }
    ]
}